{"type":"FeatureCollection","features":[{"type":"Feature","id":"440700","properties":{"name":"江门市","cp":[113.094942,22.590431],"childNum":41},"geometry":{"type":"MultiPolygon","coordinates":[["@@EBOHCFADDFNNBFCDC@IIGCE@CDAF@FBTBFFHBF@DABA@EEIGGAIAGAEDCDAHBHPbFHLNDHFJBBFBN@J@JBFFDFBFDBBF@FAFQNIDGDE@E@A@CB@AAAEMAECCMCGAC@EBGJCBE@EAE@GBOL@D@BBDFDFD@F@DEDABAFBDHJNJDDBF@DDDTLNDXHNBLDD@DCF@F@JHFD@DADC@CDAFAJDLBHFNBBDBDABABEAEDEDAHAFBDBBFBHFDDBF@HCF@NFPJHBJBJAD@JEDCJ@D@DBBBD@N@D@D@BA@C@ACA@CAABCDE@ABCCIACAAC@ACGEACCACAE@CBC@A@A@AA@AAAAAG@E@K@EAE@CCIKGOCC@EAE@AACGGEECGEQAI@IBCDCHABABC@C@E@CBC@ADABAFGBCACCEICCCAECCCACCGSEU@IBEBCHCBC@EBAFAF@DCDCBK@ECEOKYIWMOE"],["@@@@AB@@@B@B@@BB@@BA@@@A@@@AA@@A"],["@@@BA@@B@@BB@@BAB@@AA@@@AA"],["@@AB@BB@BA@@A@@A"],["@@@@CB@B@BB@BBB@BA@@@A@AAAA@"],["@@@BA@@@@B@@BB@@@@B@@A@@@AA@@A"],["@@@@@@@B@@BB@@B@@@@A@@AA@@A@"],["@@A@@B@B@@BBBA@@@@@A@@AA"],["@@A@@@AB@BB@BBB@B@@ABAA@@AA@A@"],["@@A@A@CBA@A@AAA@@@ABAB@D@B@BDBDBB@B@DA@A@@@C@@@A@@DA@@BA@@@AA@"],["@@A@A@@B@B@BEBCAKCC@C@@D@B@D@B@DABA@CAA@AB@BBDHFDBFBHBDBJDD@TEPADADABC@CCCACGAAAAAACAACACACBKA"],["@@A@AB@@@B@BBBFBB@@AB@AA@ACAAA"],["@@G@EBAB@DBBJHPJJDDBF@BA@A@E@CCCCCCAGCGCEA"],["@@DD@@BB@DBB@BAFCBAB@BB@DBBB@BD@D@B@B@@BBBB@BBB@@B@BB@BBB@@BB@BAD@BBBB@BBBB@DADA@@BCBA@AB@B@@@BB@BB@@@@A@@B@B@DBB@@@B@BBB@@@BB@B@@D@B@HCDCBA@A@@B@BBB@@@B@DCBA@A@@B@BA@A@A@A@@@@B@@@B@@ADEDA@A@@B@@@@@B@@A@@@@AA@AB@@@@A@ABA@@B@@A@@@@BCB@B@@@B@@D@@@@BA@AAABA@A@ABAB@@ABAB@BB@BB@B@@@@@@A@ACA@A@CAA@@AA@@AA@ABC@@@ACA@@CBA@@@@@@A@@AAA@@A@@EC@@@@@@@@@@@@@@@@AB@@ABC@CAAACB@@CC@@B@@A@A@@@@B@B@BC@A@@CA@C@A@@@@@@B@@A@A@C@@BA@@BC@@@EAA@A@A@@AA@AA@@AAA@ADA@@@@@@@@AAA@@ABCDAD@B@BAB@BA@@@AB@@@@@@@@@@@@@BB@@B@BBBBBBB@@@@@BB@@BBDBD@DBBA@@B@@AB@BB@BFBB@B@@BBB@@D@@@BDBDB@@@D@B@BBB@@BBB@BB@BB@BBB@B@BABA@BB@@@B@@@B@@@DBD@DBD@BFF@@BBF@@@B@@A@@BAB@B@BBBD@@B@BBBB@B@B@B@B@@ABC@ADA@@@C@@@CB@BA@ABAB@@AB@B@@@BB@B@DBB@@@BBB@@@B@@@@@BBB@BBFBBBBBBBB@BA@@@B@@B@B@@@@@@@@@@@@@B@@@B@@BB@@BB@@@BADBB@B@@A@@@ABC@CDA@@BA@@BB@@@B@@BD@@BB@@ADBB@BB@@@BDBBB@@@DA@AB@BB@@@D@@@BBB@@B@B@BAB@D@BA@@D@@@B@@@@@@BBD@B@@BB@@@BBD@@@BB@@B@B@F@@B@FAB@@ABA@@D@BBDBB@B@BBB@BAAC@AB@@A@A@C@@@C@@@@BBBA@@@ABA@A@A@@@@BABBB@BBBAF@@@BB@@A@@@A@@@@@B@@BBB@@ABA@A@A@@@@A@@@@A@BB@B@@AD@BA@AB@@A@@D@@BABAD@@ABA@A@@@BB@@@B@AA@@BA@@@@BB@@@CBABAB@BB@BBBBB@@@A@@AAAA@@@AAA@@@A@@@@BBB@B@@@@@B@@@@@BD@DBBAB@BB@@@B@@@ABABADCBABA@@@@B@BB@@@B@@@@BB@B@@B@B@BB@DBB@BAB@@ADABC@ABCFB@@@BB@D@B@B@D@B@@DA@@BA@@@@@@AA@@@@BA@@B@@@BC@AD@@@@B@@@@@AB@@A@AA@@A@@@@BB@@@ABA@@@A@A@@@A@@@AAA@C@@BBBB@@@B@@DADABA@CB@B@BAB@@@@@B@@@@@@@@B@@@@@@@@@@@@@@@@@@@@@@@@@@@@@@@@@@@@@@@B@@@@@@@@BB@@@@@@@@@@@@@@@@@@@@@@@@@@@@@@@B@@@@@@@@@B@@@@@@@@@@@@@@@@@@@@@@@@@@@@@@@@@BB@@BB@@@@@@@@@@@@@@@@@@@@@@@@@@@@@@@@@@@@@@@@@@@@@@@@@@@@@@B@@@@@@@@@@@@@@@@@@B@@@@@@@@@@@@@@@A@@@@@@B@@@@@@@@@@@@@@@@@@@@@@@@@@@@@@@@@@@@@@@@@@@@@@@@@@@@@@@@@@@@@@B@@@@@@@@@@@@@@@@@@@@@@@@@@@@@@@@@@@@@@@@@@@@@@@@@@@@@@@B@@@@@@@@@@@@@@@@@@@B@@@@@@@B@@@@@@@@@@@@@@@@@@@@@@@@@@@@@@@@@@@@@@@@@@@@@@@@@@@@@@@@@@@@@@@@A@@@@@@@@@@@@@@@@@@@@@@@@@@@@@@@@@@@@@@@@@@@@@@B@@@@BB@@@@@@@@@@@@@@@@@@@@@@@@@@@@@@@@@@@@@@@@@@@@@@@@@@@@B@@@@@@@@@@@@@@@@@@@@@@@@@@@@@@D@@@@@@@@@B@@@@@@@B@@B@@@@@@@@AB@@A@@@@@A@@A@@@@@@A@@@@@@B@@@@@B@@@@@B@@@@B@@@@@@@@@@@@@@@@@@@@@@@@@@B@@B@@B@BB@@@@@@@@@@@@@@@@@@@@@@@@@@@A@@@@@@@@B@@@@@@@@@@@@@@@@@@@@@@@@@@@@@@@@@@@@@@@@@@@@@@@@@@@B@@@@@@@@@@@@A@@@@@@@@@@@@@@@@@@@@@@@@B@@@@@@@@@@@@@@@@@@@@@@@@@@@@@B@@@@@@@@@@@@@@@@@@@@@@@@@DA@@@@@@@@@@@@@@@@@@@@@@@@@@@@@@B@@@@@@@@@@A@@@@@@@@@@@@@@@@@@@@@@@@@@@@@@@@@@@@@@@@@@@@@A@@@@@@@@@@@@@@@@@@@@@@@@@@AA@@@@@@@@@@@@@@@@@@@@@@@@@@@@@@@@@@@@@@@@@@@A@@@@@@@@@@@@@@@@@@@@@@@@@@@@@CB@BAB@@@@@@@@@@@@@@@@@@@@@@A@@@@@@@@@@@@@@@@@@@@@@@@@@@@@@@@@@@@@@@@@@@@@@@@@@@@@@@@@A@@@@@@@@@@@@@@@@@@@@@@@@@@@@@@@@@@B@@@@@@@@@@@@@@@@@@@@@@@@@@@@@@@@A@ABC@A@@@A@A@AA@@A@@CBA@@CA@@@@@AC@AAA@@@@@D@@A@@B@@@ACA@C@@A@@@@@@@@@@@B@BA@B@@@B@@@@D@@@@A@@AAA@@@@AB@@@BCB@@@@A@@BA@@@@@@@@@@DBFBDB@@@A@ABA@A@A@@@AA@AA@AA@A@@CB@@AAA@@A@A@@A@@A@AA@@A@A@@@@A@AC@AB@@@@@BA@AAAA@@@@@@@@@@@@@@A@@B@@@BA@@B@AAB@@@@B@@B@@@B@@A@CA@@@CA@@A@A@A@A@AB@B@B@D@@@ABC@@@@B@@BAB@BB@@BA@@@@D@@@@@BB@@B@B@@@@@@@A@@@@A@@@@AAA@@@@@@AAA@A@@B@D@@AAA@@A@@BA@A@AA@@A@BAB@D@BA@@AAA@@B@@@@@BA@@@A@A@AA@@B@B@@@@@BA@@@AAB@@@@A@@@@@AAB@BA@CB@@AB@@C@@AAB@BA@@BBBBBB@BB@ADBBDB@B@BBDAB@D@@B@D@B@B@BB@A@@@A@A@A@@BABAAA@ADA@@B@@A@A@AA@BC@@BAB@@@BA@A@@@@@ADA@@B@@BB@DB@B@@@B@@B@@BFBB@@@@A@@@AB@@A@@@@@A@@@@BB@@BBBBBD@@B@DA@@@@@A@ABABABA@A@@@@@@@@@@B@@@@@B@BAB@B@@D@BB@BBBB@@@@@B@@B@DA@@DA@@BAB@D@@A@@@A@@DBD@@B@B@@@B@@@@B@B@BBBBBB@B@@FBD@DBB@@B@@@B@@BBB@@@BDBBBB@@B@@B@B@BBBBB@B@@@BDBB@BB@BBB@@BAD@BBJD@@B@DBBADB@BB@D@@AFB@B@@@B@@BBB@BB@@@BB@B@@B@BA@@B@D@B@D@@DB@@@B@B@D@B@@AB@@@BBB@BBB@BB@@@@B@BAB@@@@EB@BA@A@A@A@@@@BBB@@BB@@BB@BBD@@BBB@BD@B@@@B@@BBD@B@@A@@B@B@BB@@B@@@BB@B@B@B@@@B@BB@@BA@AB@D@@B@@B@B@@BB@@DBB@@@@D@B@@@B@D@@CBCBABCB@@A@A@@BADA@@BB@FDBB@B@D@@@BA@DDB@@@@@@@@@@@@@B@@@@@@@@BA@@B@@B@B@@@D@B@D@D@@@DBF@DABBB@@@BB@@BBDBDD@BBB@@BAFA@@D@@@B@FB@@@B@D@B@D@@@B@@@@@D@@@B@B@DABA@@B@B@B@B@@@D@BA@ABADA@A@A@@BABBBBBB@FD@@@@@@BBBAB@D@BC@@@A@@B@@@B@@ABA@@BAFBDBD@B@@@B@@D@@@@BBB@@@@B@B@B@B@@DD@B@B@@@B@BB@@@@C@@BAB@@@BBBDB@@@DB@@BBB@BD@@@@@A@@@A@AA@@CB@@@@@BBB@BBBA@@B@@@B@@A@A@@@@DABB@@B@@BDC@@BBBBB@B@@@@@@AA@@ABBB@@AB@A@@@@AA@@@@A@@@A@@AA@@@AB@@@@BB@@@@B@@@AB@@B@@@@@@B@@B@B@@B@@B@@B@B@@@BB@B@@@@B@BB@BA@@@@@@B@BA@@B@BB@@@@A@@B@@@@A@@@BB@@@@@BB@@F@B@@@BB@@H@JDPIVSbULGR_DEJIREPBNBX@T@B@@@@@@@B@@@HBJDPFL@LGHEFEJOHMJKHcFY@CJwFMLOFEFCF@B@FDB@DBD@@ABA@@B@@AB@@@BADCB@@AB@JC@@DAD@BAPEFCB@JGD@FG@@DBJGDCFEDEC@A@AA@AC@BCD@BADIDBD@@E@G@@AAKBAA@@@@@@EKEYB]AGLGFOVWR_DSDWC[JGTUPKLKJOJO@@@@@ALMLQFIFYFKFGFGDEFK@E@U@M@K@GBGDIDIBISLEBC@CCMGCAC@EBEFG@EAC@ADCDEBCAAE@EAAAGIGOCGAA@CPCLAFABCDCDC@A@C@ACAAC@IBC@AACC@I@C@EB@D@@C@E@@A@AADCFCDADCPGDCDCDKBCD@FCAKCAA@@@AE@C@ABADAAECQ@QA[AMAO@CGIGGAG@I@G@ECICMCSCOIKIGQGSEICEAEAQQCDEHSKHIIIACEECECGI©GQAAQUwSUEICK@SDWRaRUFKBQCsIkSkk{ucYgUOG]Ee@UDOFIHEHW^UbQ\\YpQH[DeAICECs{uaaKOU_cqIGOCsI]ABI@eFMDIJurgTYHSDSDM@ICMUIuM{EGEEGA«gOCIAIBW@GEICMH@BADADCFADDBHA@DCF@DDFAF@FBBBDCDENAD@BFAF@@BABCDBDFDF@DD@D@BDBBBL@CFBDDBB@@D@BDDH@BDCFEFBBBD@HCHADDDAFAJFHHBBAB@LLBDFBABELBBFJZTEDDDBBA@GBEFAHDDHBJDDDABCBHFLF@BCBEDKFCFE@EBEBCBEDBFBHD@BDBHCJFDCF@DB@DBCFE@ABDHBBBDBDAB@BA@@B@BADA@@@A@@@@A@@A@BAAAA@@@ADA@@D@@@DAF@@@BBFBBB@@@BBA@@B@@A@@BA@AB@@AB@B@B@B@B@B@@BB@B@BAF@BABCBAD@DA@AB@BA@AD@@@DC@CDABA@ABA@@DA@@@AD@B@BA@AD@DB@@BCDCBA@CBCDEBCDEBA@@AA@@@@BABCB@AA@AACAC@E@E@CAC@CBA@A@C@A@@AA@@BAB@B@@A@A@@@A@@B@DA@BFB@@DBBABA@AA@@ED@B@B@BA@A@@@AB@BAB@@AAA@A@C@ABABCBABA@ABABA@CAC@ABA@A@A@A@A@A@CF@BA@A@@BA@A@A@EAA@CB@@AB@BB@@BCB@BBBB@DBB@BABB@B@BA@ABA@C@@@CB@A@AAAAAA@A@@B@BAFADBB@B@D@B@BABAD@D@B@BB@ABABA@BBAB@BB@@D@B@@@@@@B@BAB@B@@ABAB@BBBB@BBB@BBBBBBBBB@BBBBB@B@DCBA@AAA@A@A@A@ABAB@DBBB@BBB@BB@BAB@BA@E@@@@@@@@@A@@A@AA@ABABC@ABABC@A@C@CACAAAA@ABA@AACA@@A@A@ABG@EBC@A@A@@BCBAD@BADA@@B@DA@ADA@AB@DCB@DABA@C@E@ABABA@CBCFCFABABCACCAACA@@C@C@@@AD@@@BABA@A@CAA@AAA@A@ABBBABA@C@C@E@A@AB@DBB@BBDAB@D@DAD@BADC@A@CDABCDABA@ADCBABA@CDAB@@AD@DBBADBD@BABAAABC@C@E@E@A@ABA@A@CACAA@BC@CA@CBC@@BAAA@EC@@C@A@AA@A@C@A@AA@C@AAAAC@CAC@AAC@GAC@EACACAEAC@AAA@CAC@A@@B@BBB@BA@@BABABADABA@ABABAB@BD@BBBBBBD@D@@@D@BBBBBBDBDB@B@BBBBBB@BB@BBB@DBBBB@BAB@DABADCBAB@D@DADCBCBAB@BCD@@AD@@BB@DAF@@BDBBDBBB@D@BAB@B@DBBDDDBFBDDBBBB@HAH@D@D@@@BAB@BC@ABABABA@C@ABCBCB@B@BAD@B@DBFB@BB@B@D@BCDEDCBA@CBC@A@AAC@ABAD@BABBB@BABABA@C@C@EBABAD@@A@C@AAABAB@B@BAF@DBBBB@DBBDFBBBDDBBAFAD@@BBBBBD@B@LCBAB@D@B@DABAB@B@@B@BD@DBB@DBDDDDDFDFBBBBB@BBDBBBBDDFDHDFBFBB@@AD@BA@ABABCBABBDDHFH@BBD@DABABA@AD@DBBFHBDBHDHD@@B@BBB@@B@BDDB@FBDBBF@DBD@D@D@DABABBB@DBBADADAD@@A@A@@D@BDFDBDDDB@B@FBB@@E@CAC@A@C@CBC@C@AACB@BABBD@BFBH@BBDBB@DB@DBDABABC@C@CAC@C@C@@@@F@FBH@FB@BBDBDB@@B@B@D@B@BBB@B@BABA@EB@DAB@@ABB@@BDFBBBBBBBBBBB@@BBD@B@B@B@DBBBBDBBBDBD@D@@B@B@DBBDAFCDA@@@C@CDC@C@CBCD@BBFADADCBADAB@@B@DAFAFAFBBB@DBBB@FDD@D@F@DEBA@C@BD@B@D@BD@BADB@@BBB@D@BB@DADABB@BBBABCD@F@BADCDAD@DBFBFBDDBBDDFBD@DBFADAD@DBD@DBB@@BAD@F@BABABAFADADABA@AB@B@B@F@D@BFD@@BB@BBBBB@FBB@BB@BBB@BDABBBBB@@BF@BBB@DBB@@D@@@@DBDBB@B@DBBBFDHBBBDDH@BABADCDA@BBBF@B@D@BAFAD@B@BBB@BDBB@B@BAB@B@FBBBFDFDBBDDD@BAD@D@BBBBDB@BBAD@BAD@B@DBB@DBB@BD@BDB@BBD@BBFBD@FAFBBADA@AB@BAF@DA@@B@BB@B@B@BBABCB@DBBBDDFBBABE@ADBBBB@D@DDBABBFDDD@H@JADAH@DAHC@GCGECCCACB@BABADCDABAFADCDB@BBBBDD@D@D@BA@@B@B@B@AA@@@@B@B@B@BBBADAD@BA@AB@@DD@BB@@BBB@A@A@A@@@AB@BABABABABCBABCAE@A@@BC@A@A@CB@D@BBB@@BB@@A@@@@@AB@BB@BAF@DAD@BAFAF@FABAB@DA@BDBBA@A@C@CD@DA@AABA@AA@@@AA@AA@@BA@@B@@ABBB@B@@@BBB@BB@BB@B@B@@BC@@BA@@BABA@@BAB@@AB@BB@@@D@AD@BBFBBBB@BBB@@BB@BBBAB@BA@@BB@@@BB@@@BB@BBA@@B@BA@A@@@ABBB@B@B@@@BA@@BB@BDBBBB@@AB@@AB@@@BBBBBB@BA@@D@@@BBB@B@@@BAB@BBB@@DB@BBBBBD@BB@@B@B@B@B@BABA@@BBBB@@B@B@B@BBBB@@B@@AB@BBB@@@B@@B@D@@AB@F@@@B@B@@BABAD@BBBBBBB@BAB@@C@CBABCBBF@DDDDDDBFDBBDDBBBBD@@@@B@B@D@DEDABBDBBBDDBBBBBBADADADBBDBBBBBA@CDAD@BAACAAAAA@CB@AAA@ADAD@DABCBC@CDCBAD@BABC@CAAAC@C@AAAA@@A@A@A@ABABA@@@AA@@@@@@@AAEA@@@A@A@A@@@A@AB@DAB@@A@AC@BABA@ABABA@@@A@ABA@@@AAC@A@@BAD@D@B@DCDAF@B@BA@A@ABADC@CDABA@A@@@CBA@C@AD@@BBBB@BAB@D@BBBAD@@@BBBD@BBBBBD@BB@@B@BA@@BABAB@BABD@BB@@B@@ABBBD@B@BBBADB@@BBBBD@BBB@B@@@B@B@@@B@BDBBB@BBB@@@BBF@@@F@BB@@@DB@@@B@BB@B@BA@@BA@@D@@@BB@@B@@@BAB@@@B@B@BAB@@@@BB@BA@ABA@@B@@@BADCBABA@A@@B@@@B@@DA@@B@@BAB@@@@@B@@@@@@ABAB@@C@AB@B@@A@AB@BA@AB@B@@@BBB@@BBB@@B@DDFB@ABAB@@@B@BAB@DAD@@ABA@@A@@A@@B@BA@@B@BA@A@@A@BAB@B@@B@BD@DABCBABC@ABABABCBAD@DB@@D@BD@AHB@@DAD@@C@A@@BADABADABA@C@A@@@BB@B@BCBA@@DCD"],["@@CBGDCD@H@DBDFBF@BBBBCDCDAD@FDLHTDJNRBBDBDA@EBABAD@HDLFJHHDDD@D@FADCDKDCDAD@DBFBBBBF@DBDBDDDBD@DAF@BBBBDBF@DBBBDH@D@DABABABBDBDDDNHJFHDDBH@DBJBD@B@BABA@ABAD@BBBHBBDDLDJDJFD@B@BABEBCBAD@B@@B@FBBB@DBB@@A@ABABEDC@AAA@ABCDGBCACAEAEAEAAAAA@E@CAA@CCAAAAGAMEEAAAAE@C@E@CBA@GBEBCDAFCBCFCNALCFABACICEECEAQBKBI@EAAC@C@ADAACCCIEEEAEAC@EAAC@C@EFCBCBEAAAAABAACC@C@E@CDAB@FADC@E@E@G@C@CBADEDGBE@CCAAGEKEKCEACCAE@CBCHARCFADC@CAACACAE@A@GCC@C@CFCDC@E@CACIAACA"],["@@@@@@@A@@@AAB@@@B@@AB@@@@@@B@@@BA"],["@@CEACCAAB@F@HAFEF@HEHCBABC@AB@B@DFDFDDDF@DBDBBBBBDBH@JBFDJ@D@BADEFKDIAIAIGGIEGACBADCBEACACC@E"],["@@@BB@@@@@BA@@A@@@@@@@A@"],["@@@B@@@AB@@@@A@@@@@@@@A@@@@@@B@@@@"],["@@@@@A@@@@A@@@@B@@@@@@A@@B@@@@@@@@@@B@@@@@@@@@@@@@BB@@@A@@@@@@@A@@@@"],["@@BE@A@@@@@A@@@@@A@@A@@BA@@B@@A@@B@@B@@B@@A@@BBB@@@@BB@A"],["@@@BB@@A@@@@@@@AA@@@@B@@@@"],["@@A@BB@@@@B@@A@@@@@AB@@@@@CA@@@@@B@B"],["@@B@@@B@@@@@AC@@@@@@AA@@A@@@@B@@@BA@@@@@BB@@B@"],["@@B@@@@@B@@A@@@A@@@@@@@@@AA@@@@@AB@@@B@@@B"],["@@BB@@B@@@B@@@@A@@A@@AA@@@@BA@@@@@@@"],["@@AB@@@@@B@@@@BBB@@A@@@A@@@@AA@@"],["@@ABA@AB@B@BBB@B@BAB@B@@@BB@D@B@@B@@BBBBBBDDBB@@BA@@@A@C@C@AB@B@B@@@@A@AA@@A@@@ABA@A@AAAA@A@C@A@A@EAAA"],["@@@@@@@B@@@B@@@A@@B@@A@@@@A@"],["@@@B@@B@@@B@AA@@A@"],["@@AD@B@B@BBBBB@@BABABABA@AAACG@@A@@BAD"],["@@A@CB@B@B@@DBB@B@@@BCAA@AA@"],["@@AB@@@B@BBBB@@BDAB@BA@@@A@@EACA"],["@@A@@@@BBB@BB@BA@@@AAA@@A@"],["@@EDCB@B@B@@BB@B@DBB@B@BB@B@BABAB@BB@@BB@BD@F@D@BCDABA@@@AAAA@ABC@ABA@C@ACAA@ABC@AAAAAC@A@"],["@@@@BB@@@@@A@@BA@@B@@A@@A@@@A@@@A@@@@B@B"],["@@@@@@@B@@@@B@@@B@@@@B@@B@@@@@@@@@@A@AA@A@A@"],["@@C@@BABABA@C@A@AB@B@D@BBBBB@BAD@BB@D@BAF@DBD@FAFBFADABABAAAACCCA@CAA@ACAAE@CAA@"],["@@BBBBDBD@BD@BBDB@DAB@BBDD@F@B@B@BF@B@DD@@BB@@BB@DCFBDB@B@DABCB@@@D@BB@@BAAA@CCCAA@@@A@AB@DBB@BAB@@CACAAAC@@@ABABAB@@A@CCAGCAA@AAABA@ABA@CACACCCCAE@C@E@E@ABCDADABC@ABA@AD@BBBBBA@AB@@AD"],["@@@B@@B@@@B@@A@@@@@A@@A@AB@@@@"],["@@@@BA@@@@@@@@@AA@AB@@@@@B@@B@"]],"encodeOffsets":[[[115482,22082]],[[115465,22266]],[[115469,22264]],[[115563,22261]],[[115283,22200]],[[115462,22200]],[[115460,22198]],[[115382,22148]],[[115584,22135]],[[115379,22130]],[[115593,22113]],[[115446,22117]],[[115509,22082]],[[115177,23249]],[[115232,22102]],[[115749,22356]],[[115739,22373]],[[115741,22297]],[[115742,22296]],[[115745,22293]],[[115740,22321]],[[115522,22227]],[[115533,22192]],[[115531,22185]],[[115531,22181]],[[115369,22236]],[[115381,22223]],[[115385,22219]],[[115385,22148]],[[115385,22150]],[[115384,22155]],[[115381,22164]],[[115344,22110]],[[115349,22109]],[[115361,22114]],[[115286,22130]],[[115279,22107]],[[115291,22105]],[[115134,22184]],[[115060,21975]],[[115057,21983]]]}}],"UTF8Encoding":true}